prefopt/__about__.py
prefopt/__init__.py
prefopt/data.py
prefopt/experiment.py
prefopt/acquisition/__init__.py
prefopt/acquisition/base.py
prefopt/acquisition/expected_improvement.py
prefopt/model/__init__.py
prefopt/model/binary.py
prefopt/optimization/__init__.py
prefopt/optimization/base.py
prefopt/optimization/direct.py
prefopt/optimization/grid_search.py
prefopt/presenter/__init__.py
prefopt/presenter/output.py
prefopt-0.0.1.dev0.dist-info/DESCRIPTION.rst
prefopt-0.0.1.dev0.dist-info/LICENSE.txt
prefopt-0.0.1.dev0.dist-info/METADATA
prefopt-0.0.1.dev0.dist-info/RECORD
prefopt-0.0.1.dev0.dist-info/WHEEL
prefopt-0.0.1.dev0.dist-info/metadata.json
prefopt-0.0.1.dev0.dist-info/top_level.txt
